<Sysmon schemaversion="4.91">
  <EventFiltering>

    <!-- Process Creation -->
    <!-- Process Creation (reduced noise, security-relevant children) -->
<ProcessCreate onmatch="include">
  <Image condition="end with">cmd.exe</Image>
  <Image condition="end with">powershell.exe</Image>
  <Image condition="end with">pwsh.exe</Image>
  <Image condition="end with">wscript.exe</Image>
  <Image condition="end with">cscript.exe</Image>
  <Image condition="end with">mshta.exe</Image>
  <Image condition="end with">rundll32.exe</Image>
  <Image condition="end with">regsvr32.exe</Image>
  <Image condition="end with">certutil.exe</Image>
  <Image condition="end with">bitsadmin.exe</Image>
</ProcessCreate>

    <!-- File Creation (IMPORTANT) -->
    <FileCreate onmatch="include">
      <TargetFilename condition="end with">.txt</TargetFilename>
    </FileCreate>

  </EventFiltering>
</Sysmon>